vidalia/__init__.py
vidalia-0.0.1.dist-info/LICENSE
vidalia-0.0.1.dist-info/WHEEL
vidalia-0.0.1.dist-info/METADATA
vidalia-0.0.1.dist-info/RECORD
